slider/__init__.py
slider/admin.py
slider/apps.py
slider/models.py
slider/serializers.py
slider/tests.py
slider/urls.py
slider/views.py
slider/migrations/0001_initial.py
slider/migrations/__init__.py
slider/templates/index.html
slider/templates/slider_list.html
slider/templatetags/__init__.py
slider/templatetags/slider_tag.py
django_sliders-6.0.dist-info/LICENSE
django_sliders-6.0.dist-info/METADATA
django_sliders-6.0.dist-info/WHEEL
django_sliders-6.0.dist-info/top_level.txt
django_sliders-6.0.dist-info/RECORD
