Metadata-Version: 2.1
Name: django-sliders
Version: 6.0
Summary: Django Slider Template app
Home-page: UNKNOWN
Author: Namnn
Author-email: nhatnamnguyen.gtvthcm@gmail.com
Maintainer: Namnn
Maintainer-email: nhatnamnguyen.gtvthcm@gmail.com
License: MIT
Platform: UNKNOWN
Classifier: Development Status :: 5 - Production/Stable
Classifier: Environment :: Web Environment
Classifier: Intended Audience :: Developers
Classifier: License :: OSI Approved :: MIT License
Classifier: Operating System :: OS Independent
Classifier: Programming Language :: Python
Classifier: Programming Language :: Python :: 2.7
Classifier: Programming Language :: Python :: 3.4
Classifier: Programming Language :: Python :: 3.5
Classifier: Programming Language :: Python :: 3.6
Classifier: Programming Language :: Python :: 3.7
Classifier: Framework :: Django
License-File: LICENSE
Requires-Dist: django (>=2.2)
Requires-Dist: six
Requires-Dist: mock
Provides-Extra: test
Requires-Dist: pytest ; extra == 'test'
Requires-Dist: pytest-cov ; extra == 'test'
Requires-Dist: pytest-django ; extra == 'test'
Requires-Dist: pytest-flakes ; extra == 'test'
